extendedstim/__init__.py
extendedstim/Circuit/Circuit.py
extendedstim/Circuit/Code2Circuit.py
extendedstim/Code/LinearCode/BicycleCode.py
extendedstim/Code/LinearCode/DoubleBicycleCode.py
extendedstim/Code/LinearCode/DoubleBivariantBicycleCode.py
extendedstim/Code/LinearCode/FiniteEuclideanGeometryCode.py
extendedstim/Code/LinearCode/FiniteProjectiveGeometryCode.py
extendedstim/Code/LinearCode/LinearCode.py
extendedstim/Code/LinearCode/TwistedDoubleBivariantBicycleCode.py
extendedstim/Code/QuantumCode/FermionicLatticeSurgery.py
extendedstim/Code/QuantumCode/MajoranaCSSCode.py
extendedstim/Code/QuantumCode/MajoranaCode.py
extendedstim/Code/QuantumCode/MajoranaColorCode.py
extendedstim/Code/QuantumCode/PauliCSSCode.py
extendedstim/Code/QuantumCode/PauliCode.py
extendedstim/Code/QuantumCode/PauliColorCode.py
extendedstim/Code/QuantumCode/QuantumCSSCode.py
extendedstim/Code/QuantumCode/QuantumCode.py
extendedstim/Code/QuantumCode/SubsystemCode.py
extendedstim/Physics/MajoranaOperator.py
extendedstim/Physics/Operator.py
extendedstim/Physics/PauliOperator.py
extendedstim/Platform/Frame.py
extendedstim/Platform/Platform.py
extendedstim/tools/GaloisTools.py
extendedstim/tools/TypingTools.py
extendedstim-1.2.3.dist-info/licenses/LICENSE
extendedstim-1.2.3.dist-info/METADATA
extendedstim-1.2.3.dist-info/WHEEL
extendedstim-1.2.3.dist-info/top_level.txt
extendedstim-1.2.3.dist-info/RECORD
