Metadata-Version: 2.4
Name: extendedstim
Version: 1.2.3
Summary: ExtendedStim: tools for testing quantum circuits, quantum error-correction codes.
Author-email: Moke <Moke2001@whu.edu.cn>
License: MIT License
Project-URL: Homepage, https://github.com/Moke2001/ExtendedStim
Project-URL: Source, https://github.com/Moke2001/ExtendedStim
Keywords: quantum physics,quantum error-correction codes,physics,quantum circuits
Classifier: Programming Language :: Python :: 3
Classifier: License :: OSI Approved :: MIT License
Classifier: Operating System :: OS Independent
Requires-Python: >=3.12
License-File: LICENSE
Requires-Dist: qiskit
Requires-Dist: numpy
Requires-Dist: stim
Requires-Dist: scipy
Requires-Dist: matplotlib
Requires-Dist: stimbposd
Requires-Dist: pylatexenc
Requires-Dist: qutip
Requires-Dist: galois
Requires-Dist: mip
Requires-Dist: networkx
Dynamic: license-file
